{
  "resourceType" : "CodeSystem",
  "id" : "CSTipoDeViaCL",
  "text" : {
    "status" : "generated",
    "div" : "<div xmlns=\"http://www.w3.org/1999/xhtml\"><p>This case-sensitive code system <code>https://interoperabilidad.minsal.cl/fhir/ig/eis/CodeSystem/CSTipoDeViaCL</code> defines the following codes:</p><table class=\"codes\"><tr><td style=\"white-space:nowrap\"><b>Code</b></td><td><b>Display</b></td></tr><tr><td style=\"white-space:nowrap\">1<a name=\"CSTipoDeViaCL-1\"> </a></td><td>Calle</td></tr><tr><td style=\"white-space:nowrap\">2<a name=\"CSTipoDeViaCL-2\"> </a></td><td>Avenida</td></tr><tr><td style=\"white-space:nowrap\">3<a name=\"CSTipoDeViaCL-3\"> </a></td><td>Pasaje</td></tr><tr><td style=\"white-space:nowrap\">4<a name=\"CSTipoDeViaCL-4\"> </a></td><td>Camino</td></tr><tr><td style=\"white-space:nowrap\">5<a name=\"CSTipoDeViaCL-5\"> </a></td><td>Carretera</td></tr><tr><td style=\"white-space:nowrap\">6<a name=\"CSTipoDeViaCL-6\"> </a></td><td>Callej贸n</td></tr><tr><td style=\"white-space:nowrap\">7<a name=\"CSTipoDeViaCL-7\"> </a></td><td>Paseo</td></tr><tr><td style=\"white-space:nowrap\">8<a name=\"CSTipoDeViaCL-8\"> </a></td><td>Escalera</td></tr><tr><td style=\"white-space:nowrap\">9<a name=\"CSTipoDeViaCL-9\"> </a></td><td>Otro</td></tr><tr><td style=\"white-space:nowrap\">10<a name=\"CSTipoDeViaCL-10\"> </a></td><td>Rotonda</td></tr></table></div>"
  },
  "url" : "https://interoperabilidad.minsal.cl/fhir/ig/eis/CodeSystem/CSTipoDeViaCL",
  "version" : "0.1.0",
  "name" : "CSTipoDeViaCL",
  "title" : "Corresponde al tipo o clasificaci贸n de calle.",
  "status" : "active",
  "experimental" : false,
  "date" : "2022-01-18T00:00:00-03:00",
  "publisher" : "Unidad de Interoperabilidad - MINSAL",
  "contact" : [{
    "name" : "Unidad de Interoperabilidad - MINSAL",
    "telecom" : [{
      "system" : "url",
      "value" : "https://interoperabilidad.minsal.cl"
    }]
  }],
  "description" : "Corresponde al tipo o clasificaci贸n de calle.",
  "jurisdiction" : [{
    "coding" : [{
      "system" : "urn:iso:std:iso:3166",
      "code" : "CL",
      "display" : "Chile"
    }]
  }],
  "caseSensitive" : true,
  "content" : "complete",
  "count" : 10,
  "concept" : [{
    "code" : "1",
    "display" : "Calle"
  },
  {
    "code" : "2",
    "display" : "Avenida"
  },
  {
    "code" : "3",
    "display" : "Pasaje"
  },
  {
    "code" : "4",
    "display" : "Camino"
  },
  {
    "code" : "5",
    "display" : "Carretera"
  },
  {
    "code" : "6",
    "display" : "Callej贸n"
  },
  {
    "code" : "7",
    "display" : "Paseo"
  },
  {
    "code" : "8",
    "display" : "Escalera"
  },
  {
    "code" : "9",
    "display" : "Otro"
  },
  {
    "code" : "10",
    "display" : "Rotonda"
  }]
}