<?xml version="1.0" encoding="UTF-8"?>

<Coverage xmlns="http://hl7.org/fhir">
  <id value="CoberturaFONASAEjemplo"/>
  <meta>
    <profile value="https://interoperabilidad.minsal.cl/fhir/ig/nid/StructureDefinition/MINSALCobertura"/>
  </meta>
  <text>
    <status value="extensions"/><div xmlns="http://www.w3.org/1999/xhtml"><p class="res-header-id"><b>Generated Narrative: Coverage CoberturaFONASAEjemplo</b></p><a name="CoberturaFONASAEjemplo"> </a><a name="hcCoberturaFONASAEjemplo"> </a><a name="CoberturaFONASAEjemplo-es-CL"> </a><div style="display: inline-block; background-color: #d9e0e7; padding: 6px; margin: 4px; border: 1px solid #8da1b4; border-radius: 5px; line-height: 60%"><p style="margin-bottom: 0px"/><p style="margin-bottom: 0px">Profile: <a href="StructureDefinition-MINSALCobertura.html">MINSAL Cobertura de Salud del Paciente</a></p></div><p><b>status</b>: Active</p><p><b>type</b>: <span title="Codes:{https://interoperabilidad.minsal.cl/fhir/ig/nid/CodeSystem/CSPrevision 1}">FONASA</span></p><p><b>policyHolder</b>: <a href="Patient-MinsalPacienteEjemplo.html">Javiera Castilla (official) Female, DoB: 1995-12-12 ( PPN: ACL123456789876 (use: official, ))</a></p><p><b>beneficiary</b>: <a href="Patient-MinsalPacienteEjemplo.html">Javiera Castilla (official) Female, DoB: 1995-12-12 ( PPN: ACL123456789876 (use: official, ))</a></p><p><b>period</b>: 2024-01-12 --&gt; (ongoing)</p><p><b>payor</b>: <a href="Organization-FONASA.html">Organization Fondo Nacional De Salud</a></p><h3>Classes</h3><table class="grid"><tr><td style="display: none">-</td><td><b>Type</b></td><td><b>Value</b></td></tr><tr><td style="display: none">*</td><td><span title="Codes:{https://interoperabilidad.minsal.cl/fhir/ig/nid/CodeSystem/CSClasesDeCobertura 1}">Tramos de FONASA</span></td><td><code>Valor de la Clase: </code><a href="CodeSystem-CSTramosFONASA.html#CSTramosFONASA-A">Tramos de FONASA A</a>: FONASA A</td></tr></table></div>
  </text>
  <status value="active"/>
  <type>
    <coding>
      <system value="https://interoperabilidad.minsal.cl/fhir/ig/nid/CodeSystem/CSPrevision"/>
      <code value="1"/>
      <display value="FONASA"/>
    </coding>
  </type>
  <policyHolder>
    <reference value="Patient/MinsalPacienteEjemplo"/>
  </policyHolder>
  <beneficiary>
    <reference value="Patient/MinsalPacienteEjemplo"/>
  </beneficiary>
  <period>
    <start value="2024-01-12"/>
  </period>
  <payor>
    <reference value="Organization/FONASA"/>
  </payor>
  <class>
    <type>
      <coding>
        <system value="https://interoperabilidad.minsal.cl/fhir/ig/nid/CodeSystem/CSClasesDeCobertura"/>
        <code value="1"/>
        <display value="Tramos de FONASA"/>
      </coding>
    </type>
    <value>
      <extension url="https://interoperabilidad.minsal.cl/fhir/ig/nid/StructureDefinition/ValorDeLaClase">
        <valueCoding>
          <system value="https://interoperabilidad.minsal.cl/fhir/ig/nid/CodeSystem/CSTramosFONASA"/>
          <code value="A"/>
          <display value="FONASA A"/>
        </valueCoding>
      </extension>
    </value>
  </class>
</Coverage>