{
  "resourceType" : "CodeSystem",
  "id" : "58d66681-4f1e-4f03-bc5f-513bb4276184-60",
  "url" : "http://hl7.org/fhir/comparison/CodeSystem/58d66681-4f1e-4f03-bc5f-513bb4276184-60",
  "name" : "IntersectionCSUNivelAprobAndCSUNivelAprob",
  "title" : "Intersection of Último nivel aprobado And Último nivel aprobado",
  "status" : "active",
  "date" : "2025-11-28T16:24:31-03:00",
  "jurisdiction" : [{
    "coding" : [{
      "system" : "urn:iso:std:iso:3166",
      "code" : "CL",
      "display" : "Chile"
    }]
  }],
  "concept" : [{
    "code" : "1",
    "display" : "Preescolar"
  },
  {
    "code" : "2",
    "display" : "Especial o Diferencial"
  },
  {
    "code" : "3",
    "display" : "Básica o Primaria"
  },
  {
    "code" : "4",
    "display" : "Media o Secundaria"
  },
  {
    "code" : "5",
    "display" : "Educación Superior"
  },
  {
    "code" : "6",
    "display" : "Sin Instrucción"
  },
  {
    "code" : "97",
    "display" : "No Recuerda"
  },
  {
    "code" : "98",
    "display" : "No Responde"
  }]
}