{
  "codeSystems" : [
    {
      "url" : "https://interoperabilidad.minsal.cl/fhir/ig/mfr/CodeSystem/CSAmbitoFuncionamiento",
      "version" : "0.1.4",
      "status" : "active",
      "name" : "CSAmbitoFuncionamiento",
      "title" : "Ambito Funcionamiento",
      "description" : "Ambito Funcionamiento"
    },
    {
      "url" : "https://interoperabilidad.minsal.cl/fhir/ig/mfr/CodeSystem/CSCertificacionInst",
      "version" : "0.1.4",
      "status" : "active",
      "name" : "CSCertificacionInst",
      "title" : "Procedimientos de certificación",
      "description" : "Procedimientos de certificación"
    },
    {
      "url" : "https://interoperabilidad.minsal.cl/fhir/ig/mfr/CodeSystem/CSClasificacionSapu",
      "version" : "0.1.4",
      "status" : "active",
      "name" : "CSClasificacionSapu",
      "title" : "Clasificacion SAPU",
      "description" : "Clasificacion SAPU"
    },
    {
      "url" : "https://interoperabilidad.minsal.cl/fhir/ig/mfr/CodeSystem/CSDependenciaAdministrativa",
      "version" : "0.1.4",
      "status" : "active",
      "name" : "CSDependenciaAdministrativa",
      "title" : "Dependencia Administrativa",
      "description" : "Dependencia Administrativa"
    },
    {
      "url" : "https://interoperabilidad.minsal.cl/fhir/ig/mfr/CodeSystem/CSEstadoFuncionamiento",
      "version" : "0.1.4",
      "status" : "active",
      "name" : "CSEstadoFuncionamiento",
      "title" : "Estado Funcionamiento",
      "description" : "Estado Funcionamiento"
    },
    {
      "url" : "https://interoperabilidad.minsal.cl/fhir/ig/mfr/CodeSystem/CSModalidadAtencion",
      "version" : "0.1.4",
      "status" : "active",
      "name" : "CSModalidadAtencion",
      "title" : "Modalidad atención prestador",
      "description" : "Modalidad atención"
    },
    {
      "url" : "https://interoperabilidad.minsal.cl/fhir/ig/mfr/CodeSystem/CSNivelAtencion",
      "version" : "0.1.4",
      "status" : "active",
      "name" : "CSNivelAtencion",
      "title" : "Nivel Atencion",
      "description" : "Nivel de Atencion"
    },
    {
      "url" : "https://interoperabilidad.minsal.cl/fhir/ig/mfr/CodeSystem/CSNivelComplejidadEstablecimiento",
      "version" : "0.1.4",
      "status" : "active",
      "name" : "CSNivelComplejidadEstablecimiento",
      "title" : "Nivel Complejidad Establecimiento",
      "description" : "Nivel Complejidad Establecimiento"
    },
    {
      "url" : "https://interoperabilidad.minsal.cl/fhir/ig/mfr/CodeSystem/CSPertenenciaSNSS",
      "version" : "0.1.4",
      "status" : "active",
      "name" : "CSPertenenciaSNSS",
      "title" : "PertenenciaSNSS",
      "description" : "PertenenciaSNSS"
    },
    {
      "url" : "https://interoperabilidad.minsal.cl/fhir/ig/mfr/CodeSystem/CSSEREMI",
      "version" : "0.1.4",
      "status" : "active",
      "name" : "CSSeremi",
      "title" : "SEREMIs",
      "description" : "SEREMIs"
    },
    {
      "url" : "https://interoperabilidad.minsal.cl/fhir/ig/mfr/CodeSystem/CSServiciosdeSalud",
      "version" : "0.1.4",
      "status" : "active",
      "name" : "CSServiciosdeSalud",
      "title" : "Servicios de Salud",
      "description" : "Servicios de Salud"
    },
    {
      "url" : "https://interoperabilidad.minsal.cl/fhir/ig/mfr/CodeSystem/CSSexoBiologico",
      "version" : "0.1.4",
      "status" : "active",
      "name" : "CSSexoBiologico",
      "title" : "Códigos para Sexo de Nacimiento de Paciente",
      "description" : "Codigos definidos para el sexo de nacimiento de un paciente en Chile"
    },
    {
      "url" : "https://interoperabilidad.minsal.cl/fhir/ig/mfr/CodeSystem/CSTipoIdentificadorDEIS",
      "version" : "0.1.4",
      "status" : "active",
      "name" : "CSTipoIdentificadorDEIS",
      "title" : "Códigos para tipops de identificadores",
      "description" : "Códigos para lo tipos de identificadores"
    },
    {
      "url" : "https://interoperabilidad.minsal.cl/fhir/ig/mfr/CodeSystem/CSTipoUrgencia",
      "version" : "0.1.4",
      "status" : "active",
      "name" : "CSTipoUrgencia",
      "title" : "Tipo de urgencia",
      "description" : "Tipo de urgencia"
    },
    {
      "url" : "https://interoperabilidad.minsal.cl/fhir/ig/mfr/CodeSystem/CSTiposEstabPub",
      "version" : "0.1.4",
      "status" : "active",
      "name" : "CSTiposEstabPub",
      "title" : "Tipos de establecimientos públicos",
      "description" : "Tipos de establecimientos públicos"
    },
    {
      "url" : "https://interoperabilidad.minsal.cl/fhir/ig/mfr/CodeSystem/CSTiposEstabPubAPS",
      "version" : "0.1.4",
      "status" : "active",
      "name" : "CSTiposEstabPubAPS",
      "title" : "Tipos de establecimientos públicos en APS",
      "description" : "Tipos de establecimientos públicos en APS"
    },
    {
      "url" : "https://interoperabilidad.minsal.cl/fhir/ig/mfr/CodeSystem/CSTiposEstabPubEsp",
      "version" : "0.1.4",
      "status" : "active",
      "name" : "CSTiposEstabPubEsp",
      "title" : "Tipos de establecimientos públicos Especialidades",
      "description" : "Tipos de establecimientos públicos Especialidades"
    },
    {
      "url" : "https://interoperabilidad.minsal.cl/fhir/ig/mfr/CodeSystem/CSTiposEstabPubHosp",
      "version" : "0.1.4",
      "status" : "active",
      "name" : "CSTiposEstabPubHosp",
      "title" : "Tipos de establecimientos públicos Hospitales",
      "description" : "Tipos de establecimientos públicos Hospitales"
    },
    {
      "url" : "https://interoperabilidad.minsal.cl/fhir/ig/mfr/CodeSystem/CSTiposEstabPubOtros",
      "version" : "0.1.4",
      "status" : "active",
      "name" : "CSTiposEstabPubOtros",
      "title" : "Tipos de establecimientos públicos \"otros\"",
      "description" : "Tipos de establecimientos públicos \"otros\" "
    },
    {
      "url" : "https://interoperabilidad.minsal.cl/fhir/ig/mfr/CodeSystem/CSTiposPrestador",
      "version" : "0.1.4",
      "status" : "active",
      "name" : "CSTipoPrestador",
      "title" : "Tipos de prestadores",
      "description" : "Tipos de prestadores"
    }
  ]
}
