{
  "resourceType" : "CodeSystem",
  "id" : "CSTipoUrgencia",
  "text" : {
    "status" : "generated",
    "div" : "<div xmlns=\"http://www.w3.org/1999/xhtml\"><p>This case-sensitive code system <code>https://interoperabilidad.minsal.cl/fhir/ig/mfr/CodeSystem/CSTipoUrgencia</code> defines the following codes:</p><table class=\"codes\"><tr><td style=\"white-space:nowrap\"><b>Code</b></td><td><b>Display</b></td></tr><tr><td style=\"white-space:nowrap\">1<a name=\"CSTipoUrgencia-1\"> </a></td><td>Urgencia Ambulatoria SAPU</td></tr><tr><td style=\"white-space:nowrap\">2<a name=\"CSTipoUrgencia-2\"> </a></td><td>Urgencia Ambulatoria SAR</td></tr><tr><td style=\"white-space:nowrap\">3<a name=\"CSTipoUrgencia-3\"> </a></td><td>Urgencia Ambulatoria SUR</td></tr><tr><td style=\"white-space:nowrap\">4<a name=\"CSTipoUrgencia-4\"> </a></td><td>Urgencia Ambulatoria CEAR</td></tr><tr><td style=\"white-space:nowrap\">5<a name=\"CSTipoUrgencia-5\"> </a></td><td>Urgencia Ambulatoria Privada</td></tr><tr><td style=\"white-space:nowrap\">6<a name=\"CSTipoUrgencia-6\"> </a></td><td>Urgencia Ambulatoria Especializada</td></tr><tr><td style=\"white-space:nowrap\">7<a name=\"CSTipoUrgencia-7\"> </a></td><td>Urgencia Hospitalaria UEH</td></tr><tr><td style=\"white-space:nowrap\">8<a name=\"CSTipoUrgencia-8\"> </a></td><td>Urgencia Hospitalaria Especializada</td></tr><tr><td style=\"white-space:nowrap\">9<a name=\"CSTipoUrgencia-9\"> </a></td><td>Pendiente</td></tr><tr><td style=\"white-space:nowrap\">95<a name=\"CSTipoUrgencia-95\"> </a></td><td>No Aplica</td></tr></table></div>"
  },
  "url" : "https://interoperabilidad.minsal.cl/fhir/ig/mfr/CodeSystem/CSTipoUrgencia",
  "version" : "0.1.4",
  "name" : "CSTipoUrgencia",
  "title" : "Tipo de urgencia",
  "status" : "active",
  "experimental" : true,
  "date" : "2024-01-29T00:00:00-03:00",
  "publisher" : "Unidad de Interoperabilidad - MINSAL",
  "contact" : [{
    "name" : "Unidad de Interoperabilidad - MINSAL",
    "telecom" : [{
      "system" : "url",
      "value" : "https://interoperabilidad.minsal.cl"
    }]
  }],
  "description" : "Tipo de urgencia",
  "jurisdiction" : [{
    "coding" : [{
      "system" : "urn:iso:std:iso:3166",
      "code" : "CL",
      "display" : "Chile"
    }]
  }],
  "caseSensitive" : true,
  "content" : "complete",
  "count" : 10,
  "concept" : [{
    "code" : "1",
    "display" : "Urgencia Ambulatoria SAPU"
  },
  {
    "code" : "2",
    "display" : "Urgencia Ambulatoria SAR"
  },
  {
    "code" : "3",
    "display" : "Urgencia Ambulatoria SUR"
  },
  {
    "code" : "4",
    "display" : "Urgencia Ambulatoria CEAR"
  },
  {
    "code" : "5",
    "display" : "Urgencia Ambulatoria Privada"
  },
  {
    "code" : "6",
    "display" : "Urgencia Ambulatoria Especializada"
  },
  {
    "code" : "7",
    "display" : "Urgencia Hospitalaria UEH"
  },
  {
    "code" : "8",
    "display" : "Urgencia Hospitalaria Especializada"
  },
  {
    "code" : "9",
    "display" : "Pendiente"
  },
  {
    "code" : "95",
    "display" : "No Aplica"
  }]
}