{
  "resourceType" : "Patient",
  "id" : "22e862c5-6d96-44ec-869c-dba001058cb3",
  "meta" : {
    "profile" : ["https://interoperabilidad.minsal.cl/fhir/ig/quirurgico/StructureDefinition/PatientLE"]
  },
  "text" : {
    "status" : "generated",
    "div" : "<div xmlns=\"http://www.w3.org/1999/xhtml\"><p class=\"res-header-id\"><b>Generated Narrative: Paciente 22e862c5-6d96-44ec-869c-dba001058cb3</b></p><a name=\"22e862c5-6d96-44ec-869c-dba001058cb3\"> </a><a name=\"hc22e862c5-6d96-44ec-869c-dba001058cb3\"> </a><div style=\"display: inline-block; background-color: #d9e0e7; padding: 6px; margin: 4px; border: 1px solid #8da1b4; border-radius: 5px; line-height: 60%\"><p style=\"margin-bottom: 0px\"/><p style=\"margin-bottom: 0px\">Profile: <a href=\"StructureDefinition-PatientLE.html\">Patient LE</a></p></div><p style=\"border: 1px #661aff solid; background-color: #e6e6ff; padding: 10px;\">Juan Pérez (official) Male, DoB: 1980-01-01 ( RUN: 4444444-4)</p><hr/><table class=\"grid\"><tr><td style=\"background-color: #f3f5da\" title=\"Known status of Patient\">Deceased:</td><td colspan=\"3\">false</td></tr><tr><td style=\"background-color: #f3f5da\" title=\"Ways to contact the Patient\">Contact Detail</td><td colspan=\"3\">ph: 987654321</td></tr><tr><td style=\"background-color: #f3f5da\" title=\"Pueblos Originarios Perteneciente\"><a href=\"StructureDefinition-PueblosOriginariosPerteneciente.html\">Pueblos Originarios Perteneciente</a></td><td colspan=\"3\">true</td></tr><tr><td style=\"background-color: #f3f5da\" title=\"Religión\"><a href=\"StructureDefinition-Religion.html\">Religión</a></td><td colspan=\"3\"><span title=\"Codes:{https://interoperabilidad.minsal.cl/fhir/ig/quirurgico/CodeSystem/CSReligion 1}\">Católica</span></td></tr><tr><td style=\"background-color: #f3f5da\" title=\"Esta extensión incluye códigos de países\"><a href=\"https://hl7chile.cl/fhir/ig/clcore/1.9.4/StructureDefinition-CodigoPaises.html\">Código de Países</a></td><td colspan=\"3\"><span title=\"Codes:{urn:iso:std:iso:3166 152}\">Chile</span></td></tr><tr><td style=\"background-color: #f3f5da\" title=\"País de origen del paciente\"><a href=\"StructureDefinition-PaisOrigenMPI.html\">País de origen del paciente</a></td><td colspan=\"3\"><span title=\"Codes:{urn:iso:std:iso:3166 152}\">Chile</span></td></tr><tr><td style=\"background-color: #f3f5da\" title=\"Almacenar si el paciente pertenece a algun pueblo originario\"><a href=\"StructureDefinition-PueblosOriginarios.html\">Pueblos Originarios</a></td><td colspan=\"3\"><span title=\"Codes:{https://interoperabilidad.minsal.cl/fhir/ig/quirurgico/CodeSystem/PueblosOriginariosCS 01}\">Mapuche</span></td></tr><tr><td style=\"background-color: #f3f5da\" title=\"Pueblos Afrodescendiente\"><a href=\"StructureDefinition-PueblosAfrodescendiente.html\">Pueblos Afrodescendiente</a></td><td colspan=\"3\">false</td></tr><tr><td style=\"background-color: #f3f5da\" title=\"Identidad De Género\"><a href=\"https://hl7chile.cl/fhir/ig/clcore/1.9.4/StructureDefinition-IdentidadDeGenero.html\">Identidad De Género</a></td><td colspan=\"3\"><span title=\"Codes:{https://hl7chile.cl/fhir/ig/clcore/CodeSystem/CSIdentidaddeGenero 1}\">Masculino</span></td></tr></table></div>"
  },
  "extension" : [{
    "url" : "https://interoperabilidad.minsal.cl/fhir/ig/quirurgico/StructureDefinition/PaisOrigenMPI",
    "valueCodeableConcept" : {
      "coding" : [{
        "system" : "urn:iso:std:iso:3166",
        "code" : "152",
        "display" : "Chile"
      }]
    }
  },
  {
    "url" : "https://interoperabilidad.minsal.cl/fhir/ig/quirurgico/StructureDefinition/Religion",
    "valueCodeableConcept" : {
      "coding" : [{
        "system" : "https://interoperabilidad.minsal.cl/fhir/ig/quirurgico/CodeSystem/CSReligion",
        "code" : "1",
        "display" : "Católica"
      }]
    }
  },
  {
    "url" : "https://interoperabilidad.minsal.cl/fhir/ig/quirurgico/StructureDefinition/PueblosOriginariosPerteneciente",
    "valueBoolean" : true
  },
  {
    "url" : "https://interoperabilidad.minsal.cl/fhir/ig/quirurgico/StructureDefinition/PueblosAfrodescendiente",
    "valueBoolean" : false
  },
  {
    "url" : "https://interoperabilidad.minsal.cl/fhir/ig/quirurgico/StructureDefinition/PueblosOriginarios",
    "valueCodeableConcept" : {
      "coding" : [{
        "system" : "https://interoperabilidad.minsal.cl/fhir/ig/quirurgico/CodeSystem/PueblosOriginariosCS",
        "code" : "01",
        "display" : "Mapuche"
      }]
    }
  },
  {
    "url" : "https://hl7chile.cl/fhir/ig/clcore/StructureDefinition/CodigoPaises",
    "valueCodeableConcept" : {
      "coding" : [{
        "system" : "urn:iso:std:iso:3166",
        "code" : "152",
        "display" : "Chile"
      }]
    }
  },
  {
    "url" : "https://hl7chile.cl/fhir/ig/clcore/StructureDefinition/IdentidadDeGenero",
    "valueCodeableConcept" : {
      "coding" : [{
        "system" : "https://hl7chile.cl/fhir/ig/clcore/CodeSystem/CSIdentidaddeGenero",
        "code" : "1",
        "display" : "Masculino"
      }]
    }
  }],
  "identifier" : [{
    "type" : {
      "extension" : [{
        "url" : "https://hl7chile.cl/fhir/ig/clcore/StructureDefinition/CodigoPaises",
        "valueCodeableConcept" : {
          "coding" : [{
            "system" : "urn:iso:std:iso:3166",
            "code" : "152",
            "display" : "Chile"
          }]
        }
      }],
      "coding" : [{
        "system" : "https://hl7chile.cl/fhir/ig/clcore/CodeSystem/CSTipoIdentificador",
        "code" : "01",
        "display" : "RUN"
      }]
    },
    "value" : "4444444-4"
  }],
  "name" : [{
    "use" : "official",
    "family" : "Pérez",
    "_family" : {
      "extension" : [{
        "url" : "https://hl7chile.cl/fhir/ig/clcore/StructureDefinition/SegundoApellido",
        "valueString" : "Olivares"
      }]
    },
    "given" : ["Juan"]
  }],
  "telecom" : [{
    "system" : "phone",
    "value" : "987654321"
  }],
  "gender" : "male",
  "birthDate" : "1980-01-01",
  "deceasedBoolean" : false
}