{
  "resourceType" : "ValueSet",
  "id" : "TipoParticipanteEncuentroUrgencia",
  "text" : {
    "status" : "generated",
    "div" : "<div xmlns=\"http://www.w3.org/1999/xhtml\"><p class=\"res-header-id\"><b>Generated Narrative: ValueSet TipoParticipanteEncuentroUrgencia</b></p><a name=\"TipoParticipanteEncuentroUrgencia\"> </a><a name=\"hcTipoParticipanteEncuentroUrgencia\"> </a><a name=\"TipoParticipanteEncuentroUrgencia-es-CL\"> </a><p>This value set includes codes based on the following rules:</p><ul><li>Include all codes defined in <a href=\"CodeSystem-TipoParticipanteUrgencia.html\"><code>https://interoperabilidad.minsal.cl/fhir/ig/urgencia/CodeSystem/TipoParticipanteUrgencia</code></a></li><li>Include codes from<a href=\"http://terminology.hl7.org/6.0.2/CodeSystem-v3-ParticipationType.html\"><code>http://terminology.hl7.org/CodeSystem/v3-ParticipationType</code></a> where concept  is-a <a href=\"http://terminology.hl7.org/6.0.2/CodeSystem-v3-ParticipationType.html#v3-ParticipationType-ADM\">ADM</a></li><li>Include codes from<a href=\"http://terminology.hl7.org/6.0.2/CodeSystem-v3-ParticipationType.html\"><code>http://terminology.hl7.org/CodeSystem/v3-ParticipationType</code></a> where concept  is-a <a href=\"http://terminology.hl7.org/6.0.2/CodeSystem-v3-ParticipationType.html#v3-ParticipationType-ATND\">ATND</a></li><li>Include codes from<a href=\"http://terminology.hl7.org/6.0.2/CodeSystem-v3-ParticipationType.html\"><code>http://terminology.hl7.org/CodeSystem/v3-ParticipationType</code></a> where concept  is-a <a href=\"http://terminology.hl7.org/6.0.2/CodeSystem-v3-ParticipationType.html#v3-ParticipationType-CON\">CON</a></li><li>Include codes from<a href=\"http://terminology.hl7.org/6.0.2/CodeSystem-v3-ParticipationType.html\"><code>http://terminology.hl7.org/CodeSystem/v3-ParticipationType</code></a> where concept  is-a <a href=\"http://terminology.hl7.org/6.0.2/CodeSystem-v3-ParticipationType.html#v3-ParticipationType-DIS\">DIS</a></li><li>Include codes from<a href=\"http://terminology.hl7.org/6.0.2/CodeSystem-v3-ParticipationType.html\"><code>http://terminology.hl7.org/CodeSystem/v3-ParticipationType</code></a> where concept  is-a <a href=\"http://terminology.hl7.org/6.0.2/CodeSystem-v3-ParticipationType.html#v3-ParticipationType-SPRF\">SPRF</a></li><li>Include codes from<a href=\"http://terminology.hl7.org/6.0.2/CodeSystem-participant-type.html\"><code>http://terminology.hl7.org/CodeSystem/participant-type</code></a> where concept  is-a <a href=\"http://terminology.hl7.org/6.0.2/CodeSystem-participant-type.html#participant-type-emergency\">emergency</a></li></ul></div>"
  },
  "url" : "https://interoperabilidad.minsal.cl/fhir/ig/urgencia/ValueSet/TipoParticipanteEncuentroUrgencia",
  "version" : "0.1.0",
  "name" : "VSTipoParticipanteEncuentroUrgencia",
  "title" : "Tipo Participante Encuentro Urgencia",
  "status" : "draft",
  "experimental" : false,
  "date" : "2024-12-13T10:10:51-03:00",
  "publisher" : "Unidad de Interoperabilidad - MINSAL",
  "contact" : [{
    "name" : "Unidad de Interoperabilidad - MINSAL",
    "telecom" : [{
      "system" : "url",
      "value" : "https://interoperabilidad.minsal.cl"
    }]
  },
  {
    "name" : "Roberto Araneda",
    "telecom" : [{
      "system" : "email",
      "value" : "roberto.araneda@chiledata.cl",
      "use" : "work"
    }]
  },
  {
    "name" : "John Díaz",
    "telecom" : [{
      "system" : "email",
      "value" : "john.diaz@chiledata.cl",
      "use" : "work"
    }]
  }],
  "description" : "Códigos de los tipos de participante de un Encounter",
  "jurisdiction" : [{
    "coding" : [{
      "system" : "urn:iso:std:iso:3166",
      "code" : "CL",
      "display" : "Chile"
    }]
  }],
  "compose" : {
    "include" : [{
      "system" : "https://interoperabilidad.minsal.cl/fhir/ig/urgencia/CodeSystem/TipoParticipanteUrgencia"
    },
    {
      "system" : "http://terminology.hl7.org/CodeSystem/v3-ParticipationType",
      "filter" : [{
        "property" : "concept",
        "op" : "is-a",
        "value" : "ADM"
      }]
    },
    {
      "system" : "http://terminology.hl7.org/CodeSystem/v3-ParticipationType",
      "filter" : [{
        "property" : "concept",
        "op" : "is-a",
        "value" : "ATND"
      }]
    },
    {
      "system" : "http://terminology.hl7.org/CodeSystem/v3-ParticipationType",
      "filter" : [{
        "property" : "concept",
        "op" : "is-a",
        "value" : "CON"
      }]
    },
    {
      "system" : "http://terminology.hl7.org/CodeSystem/v3-ParticipationType",
      "filter" : [{
        "property" : "concept",
        "op" : "is-a",
        "value" : "DIS"
      }]
    },
    {
      "system" : "http://terminology.hl7.org/CodeSystem/v3-ParticipationType",
      "filter" : [{
        "property" : "concept",
        "op" : "is-a",
        "value" : "SPRF"
      }]
    },
    {
      "system" : "http://terminology.hl7.org/CodeSystem/participant-type",
      "filter" : [{
        "property" : "concept",
        "op" : "is-a",
        "value" : "emergency"
      }]
    }]
  }
}